LICENSE.txt
README.md
setup.py
wurst_case/__init__.py
wurst_case/main_module.py
wurst_case.egg-info/PKG-INFO
wurst_case.egg-info/SOURCES.txt
wurst_case.egg-info/dependency_links.txt
wurst_case.egg-info/top_level.txt
wurst_case/subpack/__init__.py
wurst_case/subpack/sub_m.py