Metadata-Version: 2.1
Name: wurst-case
Version: 1.0
Summary: Hi this is my first random package
Author: healpa
License-File: LICENSE.txt
